README.md
setup.py
tsukuda_fib_py/__init__.py
tsukuda_fib_py/version.py
tsukuda_fib_py.egg-info/PKG-INFO
tsukuda_fib_py.egg-info/SOURCES.txt
tsukuda_fib_py.egg-info/dependency_links.txt
tsukuda_fib_py.egg-info/entry_points.txt
tsukuda_fib_py.egg-info/requires.txt
tsukuda_fib_py.egg-info/top_level.txt
tsukuda_fib_py/cmd/__init__.py
tsukuda_fib_py/cmd/fib_numb.py
tsukuda_fib_py/fib_calcs/__init__.py
tsukuda_fib_py/fib_calcs/fib_number.py
tsukuda_fib_py/fib_calcs/fib_numbers.py
tsukuda_fib_rs/__init__.py