Metadata-Version: 2.1
Name: tsukuda-fib-py
Version: 0.0.2
Summary: Calculates a FIbonacci number
Home-page: https://github.com/tsukudamayo/tsukuda-fib-py
Author: tsukudamayo
Author-email: tsukudamayo@gmail.com
License: UNKNOWN
Platform: UNKNOWN
Classifier: Development Status :: 4 - Beta
Classifier: Programming Language :: Python :: 3
Classifier: Operating System :: OS Independent
Requires-Python: >=3
Provides-Extra: server
